LICENSE
README.md
setup.py
py_telegram_bot_api.egg-info/PKG-INFO
py_telegram_bot_api.egg-info/SOURCES.txt
py_telegram_bot_api.egg-info/dependency_links.txt
py_telegram_bot_api.egg-info/top_level.txt
telegram_bot_api/__init__.py
telegram_bot_api/api.py
telegram_bot_api/pooling.py
telegram_bot_api/utils.py