Metadata-Version: 2.1
Name: py-telegram-bot-api
Version: 0.0.8
Summary: Simple, one file, zero dependency Telegram bot api wrapper
Home-page: https://github.com/Angel777d/py-telegram-bot-api
Author: Angelovich
Author-email: angel777da@gmail.com
License: MIT
Platform: UNKNOWN
Classifier: License :: OSI Approved :: MIT License
Classifier: Programming Language :: Python :: 3
Classifier: Programming Language :: Python :: 3.6
